epsgreedy/__init__.py
epsgreedy/epsilon_greedy.py
aditya_epsgreedy_20251112-0.0.1.dist-info/METADATA
aditya_epsgreedy_20251112-0.0.1.dist-info/WHEEL
aditya_epsgreedy_20251112-0.0.1.dist-info/licenses/LICENSE
aditya_epsgreedy_20251112-0.0.1.dist-info/RECORD
